pytzer/__init__.py
pytzer/constants.py
pytzer/convert.py
pytzer/debyehueckel.py
pytzer/dissociation.py
pytzer/get.py
pytzer/meta.py
pytzer/model.py
pytzer/prepare.py
pytzer/properties.py
pytzer/teos10.py
pytzer/unsymmetrical.py
pytzer/equilibrate/__init__.py
pytzer/equilibrate/components.py
pytzer/equilibrate/solver.py
pytzer/equilibrate/thermodynamic.py
pytzer/libraries/__init__.py
pytzer/libraries/lib_CHW22.py
pytzer/libraries/lib_CRP94.py
pytzer/libraries/lib_CWTD23.py
pytzer/libraries/lib_HWT22.py
pytzer/libraries/lib_M88.py
pytzer/libraries/library_class.py
pytzer/libraries/archive/Clegg22.py
pytzer/libraries/archive/Clegg23.py
pytzer/libraries/archive/Clegg94.py
pytzer/libraries/archive/Greenberg89.py
pytzer/libraries/archive/Harvie84.py
pytzer/libraries/archive/HeMorse93.py
pytzer/libraries/archive/Humphreys22.py
pytzer/libraries/archive/MarChemSpec.py
pytzer/libraries/archive/MarChemSpec25.py
pytzer/libraries/archive/Millero98.py
pytzer/libraries/archive/MilleroThurmond83.py
pytzer/libraries/archive/Moller88.py
pytzer/libraries/archive/MyMarChemSpecCO2.py
pytzer/libraries/archive/Seawater.py
pytzer/libraries/archive/Waters13.py
pytzer/libraries/archive/Waters13_Clegg22.py
pytzer/libraries/archive/Waters13_Humphreys22.py
pytzer/libraries/archive/Waters13_MarChemSpec25.py
pytzer/parameters/__init__.py
pytzer/parameters/heMorse1993.py
pytzer/parameters/holmes1987.py
pytzer/parameters/holmesMesmer1992.py
pytzer/parameters/pabalanPitzer1987.py
pytzer/parameters/spencer1990.py
Pytzer-0.6.0.dist-info/LICENSE
Pytzer-0.6.0.dist-info/METADATA
Pytzer-0.6.0.dist-info/WHEEL
Pytzer-0.6.0.dist-info/top_level.txt
Pytzer-0.6.0.dist-info/RECORD
